sgfcmed/__init__.py
sgfcmed/sgfcmed_parallel.py
tests/__init__.py
tests/test_sgfcmed.py
python_string_fuzzy_clustering-0.0.3.dist-info/LICENSE
python_string_fuzzy_clustering-0.0.3.dist-info/METADATA
python_string_fuzzy_clustering-0.0.3.dist-info/WHEEL
python_string_fuzzy_clustering-0.0.3.dist-info/top_level.txt
python_string_fuzzy_clustering-0.0.3.dist-info/RECORD
