Metadata-Version: 2.1
Name: python-string-fuzzy-clustering
Version: 0.0.3
Summary: A simple library for String Grammar Fuzzy C-Medians
Author: Atcharin Klomsae
Author-email: atcharin.k@gmail.com
License: GPLv3
Requires-Python: >=3.7
License-File: LICENSE
Requires-Dist: pytest
